{"chunk_definitions":[{"row":32,"row_count":1,"visible":true,"expansion_state":0,"options":{"engine":"r","label":"unnamed-chunk-1","dev":"png"},"document_id":"8016D8D1","chunk_id":"ctdxsctdj4djx","chunk_label":"unnamed-chunk-1"},{"row":38,"row_count":1,"visible":true,"expansion_state":0,"options":{"engine":"r","label":"unnamed-chunk-6","dev":"png"},"document_id":"8016D8D1","chunk_id":"c65g4p3st9ze8","chunk_label":"unnamed-chunk-2"},{"row":50,"row_count":1,"visible":true,"expansion_state":0,"options":{"engine":"r","label":"unnamed-chunk-7","dev":"png"},"document_id":"8016D8D1","chunk_id":"cy40hmqjmvhrz","chunk_label":"unnamed-chunk-3"},{"row":57,"row_count":1,"visible":true,"expansion_state":0,"options":{"engine":"r","label":"unnamed-chunk-10","dev":"png"},"document_id":"8016D8D1","chunk_id":"c02bk1vo3opka","chunk_label":"unnamed-chunk-4"},{"row":62,"row_count":1,"visible":true,"expansion_state":0,"options":{"engine":"r","label":"unnamed-chunk-11","dev":"png"},"document_id":"8016D8D1","chunk_id":"cudmnrhm16czo","chunk_label":"unnamed-chunk-5"},{"row":70,"row_count":1,"visible":true,"expansion_state":0,"options":{"engine":"r","label":"unnamed-chunk-14","dev":"png"},"document_id":"8016D8D1","chunk_id":"c0shtyl6l5gjm","chunk_label":"unnamed-chunk-6"},{"row":74,"row_count":1,"visible":true,"expansion_state":0,"options":{"engine":"r","label":"unnamed-chunk-15","dev":"png"},"document_id":"8016D8D1","chunk_id":"cbcth5lodmfty","chunk_label":"unnamed-chunk-7"},{"row":84,"row_count":1,"visible":true,"expansion_state":0,"options":{"engine":"r","label":"unnamed-chunk-18","dev":"png"},"document_id":"8016D8D1","chunk_id":"cwy0zwec0hg9f","chunk_label":"unnamed-chunk-8"},{"row":93,"row_count":1,"visible":true,"expansion_state":0,"options":{"engine":"r","label":"unnamed-chunk-19","dev":"png"},"document_id":"8016D8D1","chunk_id":"ccv6notu3xxfh","chunk_label":"unnamed-chunk-9"},{"row":100,"row_count":1,"visible":true,"expansion_state":0,"options":{"engine":"r","label":"unnamed-chunk-20","dev":"png"},"document_id":"8016D8D1","chunk_id":"csurkrx05v8mn","chunk_label":"unnamed-chunk-10"},{"row":106,"row_count":1,"visible":true,"expansion_state":0,"options":{"engine":"r","label":"unnamed-chunk-21","dev":"png"},"document_id":"8016D8D1","chunk_id":"cak6xktez4wdv","chunk_label":"unnamed-chunk-11"},{"row":110,"row_count":1,"visible":true,"expansion_state":0,"options":{"engine":"r","label":"unnamed-chunk-22","dev":"png"},"document_id":"8016D8D1","chunk_id":"c4dvmwpf59gp5","chunk_label":"unnamed-chunk-12"},{"row":122,"row_count":1,"visible":true,"expansion_state":0,"options":{"engine":"r","label":"unnamed-chunk-23","dev":"png"},"document_id":"8016D8D1","chunk_id":"crfbyaky61aq9","chunk_label":"unnamed-chunk-13"},{"row":129,"row_count":1,"visible":true,"expansion_state":0,"options":{"engine":"r","label":"unnamed-chunk-25","dev":"png"},"document_id":"8016D8D1","chunk_id":"criz3sfe8knbw","chunk_label":"unnamed-chunk-14"},{"row":136,"row_count":1,"visible":true,"expansion_state":0,"options":{"engine":"r","label":"unnamed-chunk-28","dev":"png"},"document_id":"8016D8D1","chunk_id":"cszfibcd8tp3b","chunk_label":"unnamed-chunk-15"},{"row":142,"row_count":1,"visible":true,"expansion_state":0,"options":{"engine":"r","label":"unnamed-chunk-29","dev":"png"},"document_id":"8016D8D1","chunk_id":"cqc1m18z2s232","chunk_label":"unnamed-chunk-16"},{"row":157,"row_count":1,"visible":true,"expansion_state":0,"options":{"engine":"r","label":"unnamed-chunk-37","dev":"png"},"document_id":"8016D8D1","chunk_id":"cjtfj4a4rwlim","chunk_label":"unnamed-chunk-17"},{"row":199,"row_count":1,"visible":true,"expansion_state":0,"options":{"engine":"r","label":"unnamed-chunk-46","dev":"png"},"document_id":"8016D8D1","chunk_id":"cnz01qts6j254","chunk_label":"unnamed-chunk-18"},{"row":204,"row_count":1,"visible":true,"expansion_state":0,"options":{"engine":"r","label":"unnamed-chunk-41","dev":"png"},"document_id":"8016D8D1","chunk_id":"cng8taeh6olp5","chunk_label":"unnamed-chunk-19"},{"row":208,"row_count":1,"visible":true,"expansion_state":0,"options":{"engine":"r","label":"unnamed-chunk-42","dev":"png"},"document_id":"8016D8D1","chunk_id":"c26svu8mdv80k","chunk_label":"unnamed-chunk-20"},{"row":212,"row_count":1,"visible":true,"expansion_state":0,"options":{"engine":"r","label":"unnamed-chunk-47","dev":"png"},"document_id":"8016D8D1","chunk_id":"cpbwv3gk9jbjg","chunk_label":"unnamed-chunk-21"},{"row":225,"row_count":1,"visible":true,"expansion_state":0,"options":{"engine":"r","label":"unnamed-chunk-53","dev":"png"},"document_id":"8016D8D1","chunk_id":"c4ub3l5im4e8o","chunk_label":"unnamed-chunk-22"},{"row":235,"row_count":1,"visible":true,"expansion_state":0,"options":{"engine":"r","label":"unnamed-chunk-56","dev":"png"},"document_id":"8016D8D1","chunk_id":"cr32806ionv4n","chunk_label":"unnamed-chunk-23"},{"row":242,"row_count":1,"visible":true,"expansion_state":0,"options":{"engine":"r","label":"unnamed-chunk-57","dev":"png"},"document_id":"8016D8D1","chunk_id":"c1q7li1x81m3n","chunk_label":"unnamed-chunk-24"},{"row":247,"row_count":1,"visible":true,"expansion_state":0,"options":{"engine":"r","label":"unnamed-chunk-58","dev":"png"},"document_id":"8016D8D1","chunk_id":"cd1tzweloc9h0","chunk_label":"unnamed-chunk-25"},{"row":253,"row_count":1,"visible":true,"expansion_state":0,"options":{"engine":"r","label":"unnamed-chunk-59","dev":"png"},"document_id":"8016D8D1","chunk_id":"cpfldbr7hkw16","chunk_label":"unnamed-chunk-26"},{"row":258,"row_count":1,"visible":true,"expansion_state":0,"options":{"engine":"r","label":"unnamed-chunk-61","dev":"png"},"document_id":"8016D8D1","chunk_id":"c02g5uuv6jg0g","chunk_label":"unnamed-chunk-27"},{"row":267,"row_count":1,"visible":true,"expansion_state":0,"options":{"engine":"r","label":"unnamed-chunk-64","dev":"png"},"document_id":"8016D8D1","chunk_id":"cu8feoj82qpcu","chunk_label":"unnamed-chunk-28"}],"doc_write_time":1776434975}